{
  "trainingPhrases": [ {
    "parts": [ {
      "text": "w pokojach",
      "auto": true
    } ],
    "repeatCount": 1,
    "languageCode": "pl"
  }, {
    "parts": [ {
      "text": "w pomieszczeniach",
      "auto": true
    } ],
    "repeatCount": 1,
    "languageCode": "pl"
  }, {
    "parts": [ {
      "text": "pokoje",
      "parameterId": "location",
      "auto": true
    } ],
    "repeatCount": 1,
    "languageCode": "pl"
  }, {
    "parts": [ {
      "text": "pomieszczenia",
      "auto": true
    } ],
    "repeatCount": 1,
    "languageCode": "pl"
  }, {
    "parts": [ {
      "text": "nie ",
      "auto": true
    }, {
      "text": "tylko",
      "parameterId": "location",
      "auto": true
    } ],
    "repeatCount": 1,
    "languageCode": "pl"
  }, {
    "parts": [ {
      "text": "nie",
      "parameterId": "language",
      "auto": true
    } ],
    "repeatCount": 1,
    "languageCode": "pl"
  } ]
}
